Metadata-Version: 2.1
Name: hapic
Version: 0.67a1
Summary: HTTP api input/output manager
Home-page: https://github.com/algoo/hapic
Author: Algoo Development Team
Author-email: contact@algoo.fr
License: MIT
Keywords: http api validation
Platform: UNKNOWN
Requires-Dist: apispec (>=1.0.0b5)
Requires-Dist: multidict
Requires-Dist: pyyaml
Provides-Extra: dev
Requires-Dist: requests; extra == 'dev'
Requires-Dist: pytest; extra == 'dev'
Requires-Dist: pytest-cov; extra == 'dev'
Requires-Dist: bottle; extra == 'dev'
Requires-Dist: flask; extra == 'dev'
Requires-Dist: pyramid; extra == 'dev'
Requires-Dist: webtest; extra == 'dev'
Requires-Dist: aiohttp; extra == 'dev'
Requires-Dist: pytest-aiohttp; extra == 'dev'
Requires-Dist: pillow; extra == 'dev'
Requires-Dist: marshmallow (<3.0.0rc1); extra == 'dev'
Requires-Dist: apispec-marshmallow-advanced (>=0.3); extra == 'dev'
Requires-Dist: apispec-serpyco (>=0.9); extra == 'dev'
Requires-Dist: serpyco; extra == 'dev'
Provides-Extra: marshmallow
Requires-Dist: marshmallow (<3.0.0rc1); extra == 'marshmallow'
Requires-Dist: apispec-marshmallow-advanced (>=0.3); extra == 'marshmallow'
Provides-Extra: serpyco
Requires-Dist: apispec-serpyco (>=0.9); extra == 'serpyco'
Requires-Dist: serpyco; extra == 'serpyco'
Provides-Extra: test
Requires-Dist: pytest; extra == 'test'
Requires-Dist: pytest-cov; extra == 'test'
Requires-Dist: bottle; extra == 'test'
Requires-Dist: flask; extra == 'test'
Requires-Dist: pyramid; extra == 'test'
Requires-Dist: webtest; extra == 'test'
Requires-Dist: aiohttp; extra == 'test'
Requires-Dist: pytest-aiohttp; extra == 'test'
Requires-Dist: pillow; extra == 'test'
Requires-Dist: apispec-serpyco (>=0.9); extra == 'test'
Requires-Dist: serpyco; extra == 'test'
Requires-Dist: marshmallow (<3.0.0rc1); extra == 'test'
Requires-Dist: apispec-marshmallow-advanced (>=0.3); extra == 'test'
Provides-Extra: test_marshmallow
Requires-Dist: pytest; extra == 'test_marshmallow'
Requires-Dist: pytest-cov; extra == 'test_marshmallow'
Requires-Dist: bottle; extra == 'test_marshmallow'
Requires-Dist: flask; extra == 'test_marshmallow'
Requires-Dist: pyramid; extra == 'test_marshmallow'
Requires-Dist: webtest; extra == 'test_marshmallow'
Requires-Dist: aiohttp; extra == 'test_marshmallow'
Requires-Dist: pytest-aiohttp; extra == 'test_marshmallow'
Requires-Dist: pillow; extra == 'test_marshmallow'
Requires-Dist: marshmallow (<3.0.0rc1); extra == 'test_marshmallow'
Requires-Dist: apispec-marshmallow-advanced (>=0.3); extra == 'test_marshmallow'
Provides-Extra: test_serpyco
Requires-Dist: pytest; extra == 'test_serpyco'
Requires-Dist: pytest-cov; extra == 'test_serpyco'
Requires-Dist: bottle; extra == 'test_serpyco'
Requires-Dist: flask; extra == 'test_serpyco'
Requires-Dist: pyramid; extra == 'test_serpyco'
Requires-Dist: webtest; extra == 'test_serpyco'
Requires-Dist: aiohttp; extra == 'test_serpyco'
Requires-Dist: pytest-aiohttp; extra == 'test_serpyco'
Requires-Dist: pillow; extra == 'test_serpyco'
Requires-Dist: apispec-serpyco (>=0.9); extra == 'test_serpyco'
Requires-Dist: serpyco; extra == 'test_serpyco'
